EDS_mod/EDS.py
EDS_mod/EDS_mod.py
EDS_mod/__init__.py
eds_mod-1.0.4.dist-info/METADATA
eds_mod-1.0.4.dist-info/WHEEL
eds_mod-1.0.4.dist-info/licenses/LICENSE
eds_mod-1.0.4.dist-info/RECORD
